nonebot_plugin_asmr/__init__.py
nonebot_plugin_asmr-0.1.4.dist-info/LICENSE
nonebot_plugin_asmr-0.1.4.dist-info/METADATA
nonebot_plugin_asmr-0.1.4.dist-info/WHEEL
nonebot_plugin_asmr-0.1.4.dist-info/RECORD
