Metadata-Version: 2.1
Name: nonebot-plugin-asmr
Version: 0.1.4
Summary: 一个简易的能在群里听音声的插件
Home-page: https://github.com/CCYellowStar2/nonebot-plugin-asmr
License: GPL-3.0-only
Author: CCYellowStar
Requires-Python: >=3.9,<4
Classifier: License :: OSI Approved :: GNU General Public License v3 (GPLv3)
Classifier: Programming Language :: Python :: 3
Classifier: Programming Language :: Python :: 3.9
Classifier: Programming Language :: Python :: 3.10
Classifier: Programming Language :: Python :: 3.11
Classifier: Programming Language :: Python :: 3.12
Requires-Dist: aiohttp (>=3.8.4,<4)
Requires-Dist: nonebot-adapter-onebot (>=2.2.3)
Requires-Dist: nonebot-plugin-htmlrender (>=0.3.1)
Requires-Dist: nonebot2 (>=2.2.1)
Project-URL: Repository, https://github.com/CCYellowStar2/nonebot-plugin-asmr
